lessrpc_common
