Metadata-Version: 1.2
Name: lessrpc-common
Version: 1.0.10
Summary: Less RPC Common modules share between stubs, name server and extensions
Home-page: https://github.com/LessRPC/lessrpc_common_py2x
Author: Salim Malakouti
Author-email: salim.malakouti@gmail.com
License: MIT
Download-URL: https://codeload.github.com/LessRPC/lessrpc_common_py2x/tar.gz/1.0.10
Keywords: python,serialization,deserialization,rpc,rmi,less rpc
Platform: UNKNOWN
Classifier: Programming Language :: Python :: 2.7
Requires-Python: ~=2.7
